{
    "target_eff_poses": [
        [
            [
                -0.6732698082923889,
                -0.3849417269229889,
                0.6639518737792969
            ],
            [
                -0.3622398376464844,
                0.21316435933113098,
                0.1404615193605423,
                0.896445095539093
            ]
        ]
    ],
    "start_goal_config": [
        null
    ],
    "start_config": [
        [
            -3.3926130562737926,
            -2.09437865617139,
            1.2085433958959495,
            -1.6107863898379056,
            -1.7312862718875566,
            1.399472849469488e-05
        ]
    ],
    "goal_config": [
        [
            -3.610637904020715,
            -2.4744015360552276,
            1.548312735448431,
            -1.347915281815587,
            -2.4542931744456147,
            3.124961095477224e-05
        ]
    ],
    "base_poses": [
        [
            [
                -0.6752831506953291,
                -0.41360557387438157,
                0.0
            ],
            [
                0.0,
                0.0,
                -0.6736209003469947,
                0.7390770478209321
            ]
        ]
    ],
    "difficulty": 0.0,
    "dynamic_speed": null
}