{
    "target_eff_poses": [
        [
            [
                -0.09997032582759857,
                0.9110645055770874,
                0.5573769211769104
            ],
            [
                -0.40880486369132996,
                0.25396856665611267,
                0.7105284333229065,
                0.5133494734764099
            ]
        ],
        [
            [
                1.144323706626892,
                0.506676197052002,
                0.46399155259132385
            ],
            [
                -0.14580199122428894,
                0.5641030669212341,
                0.084161676466465,
                0.8083602786064148
            ]
        ]
    ],
    "start_goal_config": [
        null,
        null
    ],
    "start_config": [
        [
            -3.814390044350536,
            -1.4913942328011354,
            1.6594416393671911,
            -1.5522879555776439,
            -1.7524099980957686,
            1.696473710088694e-05
        ],
        [
            -3.708044994698195,
            -1.677799736028006,
            1.9525743036796461,
            -1.376955777016892,
            -1.7686598576102075,
            1.803216864369559e-05
        ]
    ],
    "goal_config": [
        [
            -3.5674634738029667,
            -1.3553168627397676,
            1.0666558137934103,
            -1.848722181568813,
            -1.6405666568826043,
            8.12658637877101e-06
        ],
        [
            -3.816322768011289,
            -1.362420351080414,
            1.2336054856597207,
            -1.7688255860293924,
            -1.7199927552905108,
            1.4947669437113407e-05
        ]
    ],
    "base_poses": [
        [
            [
                0.2265352089699797,
                0.3787934586885604,
                0.0
            ],
            [
                0.0,
                0.0,
                -0.3689118004816023,
                0.9294644067770549
            ]
        ],
        [
            [
                0.6061129902906384,
                0.21026527547681462,
                0.0
            ],
            [
                0.0,
                0.0,
                0.869943430015859,
                -0.49315152698966896
            ]
        ]
    ],
    "difficulty": 0.6464779460171165,
    "dynamic_speed": null
}