{
    "target_eff_poses": [
        [
            [
                0.2725919485092163,
                -0.06569156795740128,
                0.19539299607276917
            ],
            [
                -0.5689337849617004,
                0.6428293585777283,
                0.3497410714626312,
                0.37518784403800964
            ]
        ]
    ],
    "start_goal_config": [
        null
    ],
    "start_config": [
        [
            -2.693497672004604,
            -2.509460691434986,
            1.7757566538377365,
            -1.2169836298483852,
            -1.4327546224264271,
            -1.2542299040119625e-05
        ]
    ],
    "goal_config": [
        [
            -3.0046134611168234,
            -1.4405732396946849,
            1.8492478355297637,
            -1.4858341112566924,
            -1.5449757906840116,
            4.66063080929905e-06
        ]
    ],
    "base_poses": [
        [
            [
                0.34270621562588865,
                -0.511372051689418,
                0.0
            ],
            [
                0.0,
                0.0,
                -0.7844955801846621,
                0.620134408552477
            ]
        ]
    ],
    "difficulty": 0.0,
    "dynamic_speed": null
}