{
    "target_eff_poses": [
        [
            [
                0.5340664982795715,
                0.2571032643318176,
                0.2811192572116852
            ],
            [
                -0.13067413866519928,
                0.8375522494316101,
                -0.11540865153074265,
                0.517794668674469
            ]
        ],
        [
            [
                -0.31389591097831726,
                -0.43508800864219666,
                0.43975597620010376
            ],
            [
                -0.6275485157966614,
                0.21539898216724396,
                0.741792619228363,
                0.09762079268693924
            ]
        ]
    ],
    "start_goal_config": [
        null,
        null
    ],
    "start_config": [
        [
            -3.5078170680913394,
            -2.517511740931214,
            2.05514928969077,
            -1.0542292500284145,
            -1.9721267005029377,
            3.4564351454900655e-11
        ],
        [
            -4.011291446255908,
            -1.312105699985234,
            1.1074774101788796,
            -1.835778998854492,
            -1.7685974728650173,
            1.7190979942697378e-05
        ]
    ],
    "goal_config": [
        [
            -3.1697709066009327,
            -2.6403480057623674,
            2.2809690769346984,
            -0.758999212041989,
            -1.944864844874091,
            7.048882652528801e-06
        ],
        [
            -2.4550660532411035,
            -1.6163155666266242,
            1.5110358666142871,
            -1.5853729442906965,
            -1.3710063538696802,
            -7.081106822602801e-06
        ]
    ],
    "base_poses": [
        [
            [
                0.5034457105438228,
                0.19730591870295466,
                0.0
            ],
            [
                0.0,
                0.0,
                0.9998348972513841,
                0.01817080731047308
            ]
        ],
        [
            [
                0.1759327282473191,
                -0.5279685524480655,
                0.0
            ],
            [
                0.0,
                0.0,
                -0.543004339164719,
                0.8397298896956609
            ]
        ]
    ],
    "difficulty": 0.35410205807724837,
    "dynamic_speed": null
}