{
    "target_eff_poses": [
        [
            [
                0.19001458585262299,
                -0.1678490787744522,
                0.8370537161827087
            ],
            [
                0.021187003701925278,
                0.15685869753360748,
                -0.36737170815467834,
                0.9165067076683044
            ]
        ],
        [
            [
                -0.13892313838005066,
                1.0199801921844482,
                0.17676638066768646
            ],
            [
                -0.6112366914749146,
                0.6389347910881042,
                0.3473554253578186,
                0.3122439682483673
            ]
        ]
    ],
    "start_goal_config": [
        null,
        null
    ],
    "start_config": [
        [
            -3.0375309647979853,
            -2.572301405739547,
            1.1566449712453264,
            -1.508854666844251,
            -1.4745364800412728,
            5.8181234516236796e-06
        ],
        [
            -2.99191003892342,
            -2.8699591902198756,
            1.9271807427447423,
            -0.9868929469777526,
            -1.8603346560919725,
            4.790346500169691e-09
        ]
    ],
    "goal_config": [
        [
            -3.2308016892513516,
            -2.2299240117135875,
            1.058280323449215,
            -1.6520401038196502,
            -1.8178204761646046,
            1.8122331458774697e-05
        ],
        [
            -2.79795768446788,
            -1.4841804472668254,
            1.9476938389090692,
            -1.435455082462309,
            -1.4954626487784686,
            1.3840427404988578e-06
        ]
    ],
    "base_poses": [
        [
            [
                0.11578701457213358,
                -0.21471246420025492,
                0.0
            ],
            [
                0.0,
                0.0,
                0.9773775615755541,
                0.2115020144788791
            ]
        ],
        [
            [
                -0.0078611719965892,
                0.6311243722255442,
                0.0
            ],
            [
                0.0,
                0.0,
                -0.8085595817600055,
                0.5884143121509581
            ]
        ]
    ],
    "difficulty": 0.3130819147935672,
    "dynamic_speed": null
}