{
    "target_eff_poses": [
        [
            [
                -0.8999708890914917,
                0.29547831416130066,
                0.5609373450279236
            ],
            [
                -0.019960803911089897,
                -0.040779680013656616,
                0.4114322364330292,
                0.9103087782859802
            ]
        ],
        [
            [
                -0.731873095035553,
                0.8928444981575012,
                0.1230645626783371
            ],
            [
                -0.5737542510032654,
                0.7518779635429382,
                0.30770203471183777,
                0.10394806414842606
            ]
        ],
        [
            [
                -0.663835346698761,
                0.05317718908190727,
                0.18037354946136475
            ],
            [
                0.7705563306808472,
                0.07152899354696274,
                -0.6311318874359131,
                0.05290770158171654
            ]
        ]
    ],
    "start_goal_config": [
        null,
        null,
        null
    ],
    "start_config": [
        [
            -3.0180714827456563,
            -2.654360884639451,
            1.3382982754058248,
            -1.3921682869410819,
            -1.123663415885873,
            -3.115192601816348e-05
        ],
        [
            -2.4246171315505665,
            -2.1029543747763166,
            2.0514563482602304,
            -1.2032090714650028,
            -1.3961188613966233,
            -4.867214794078225e-06
        ],
        [
            -2.8803298290483395,
            -2.7911683310236657,
            1.5435155785211114,
            -1.2541273978311627,
            -2.374641688090825,
            2.6316235387993528e-05
        ]
    ],
    "goal_config": [
        [
            -3.350365104042512,
            -3.128527808055648,
            1.178976747390479,
            -1.282870510339832,
            -0.691182675914152,
            -1.0541018458409832e-05
        ],
        [
            -1.8425026968391223,
            -1.5550416995428185,
            2.2465487217968403,
            -1.3530696770237263,
            -0.9776266321170143,
            -1.2881606422605502e-05
        ],
        [
            -3.311413323303345,
            -1.0904910061668043,
            1.4542372316675998,
            -1.7354823013257286,
            -1.5797238522187105,
            4.120976445249631e-06
        ]
    ],
    "base_poses": [
        [
            [
                -0.41055230632502604,
                0.07106976439185253,
                0.0
            ],
            [
                0.0,
                0.0,
                0.9960358436161888,
                -0.08895278653188558
            ]
        ],
        [
            [
                -0.4693324229014051,
                0.6839933936290146,
                0.0
            ],
            [
                0.0,
                0.0,
                0.9556705653875418,
                -0.29443805876933804
            ]
        ],
        [
            [
                -0.06248840455079241,
                0.2699332160610388,
                0.0
            ],
            [
                -0.0,
                -0.0,
                0.1721490051049163,
                0.9850709213256614
            ]
        ]
    ],
    "difficulty": 0.7706197686447851,
    "dynamic_speed": null,
    "ur5_count": 3,
    "id": "001547",
    "task_path": "/home/hqh2101/workspace-sharing-multiarm/src/data/8f14d7-hard-vlo-tasks/001547.json"
}