{
    "target_eff_poses": [
        [
            [
                0.055083297193050385,
                -0.6483511328697205,
                0.2851869463920593
            ],
            [
                0.35727962851524353,
                0.7528727054595947,
                -0.40064167976379395,
                0.38081538677215576
            ]
        ]
    ],
    "start_goal_config": [
        null
    ],
    "start_config": [
        [
            -1.2738285192037189,
            -1.1999705680003196,
            1.7504533330891408,
            -1.582297957619224,
            -0.620912836691445,
            -2.4857375543470442e-05
        ]
    ],
    "goal_config": [
        [
            -4.200022078203886,
            -1.7673373572924842,
            1.9525019843707248,
            -1.3564772466296648,
            -1.9384627999328878,
            3.0404185966464984e-05
        ]
    ],
    "base_poses": [
        [
            [
                -0.1110063418042273,
                -0.3423082890278501,
                0.0
            ],
            [
                0.0,
                0.0,
                0.9952316800882898,
                0.0975392379949738
            ]
        ]
    ],
    "difficulty": 0.0,
    "dynamic_speed": null
}