{
    "target_eff_poses": [
        [
            [
                -0.11121679842472076,
                -0.8344017863273621,
                0.3624511659145355
            ],
            [
                0.7465440630912781,
                0.10333897173404694,
                -0.520690381526947,
                0.40109166502952576
            ]
        ]
    ],
    "start_goal_config": [
        null
    ],
    "start_config": [
        [
            -2.561587812421246,
            -1.9635532946747898,
            1.4033841805134815,
            -1.5484376753217555,
            -1.3770153689071658,
            -5.178225612810553e-06
        ]
    ],
    "goal_config": [
        [
            -1.7217614082507164,
            -1.6314804303034314,
            1.6983440536729337,
            -1.5012141228511002,
            -1.0519759904787358,
            -1.6736786370137413e-05
        ]
    ],
    "base_poses": [
        [
            [
                0.07626348269244776,
                -0.3960645224959729,
                0.0
            ],
            [
                0.0,
                0.0,
                -0.30787857383347456,
                0.9514256585641706
            ]
        ]
    ],
    "difficulty": 0.0,
    "dynamic_speed": null
}