{
    "target_eff_poses": [
        [
            [
                0.7914584875106812,
                -0.04150218516588211,
                0.2211262583732605
            ],
            [
                0.7506112456321716,
                0.5633565783500671,
                0.009617537260055542,
                0.34513720870018005
            ]
        ]
    ],
    "start_goal_config": [
        null
    ],
    "start_config": [
        [
            -4.601794201620635,
            -1.0069905329769568,
            1.3477071905427982,
            -1.7926157017460496,
            -1.9816611336173648,
            3.3860839891832716e-05
        ]
    ],
    "goal_config": [
        [
            -1.8723762200266125,
            -2.420530540981755,
            2.491592487464125,
            -0.7761094298099698,
            -0.6159883440345582,
            -9.42922984563281e-06
        ]
    ],
    "base_poses": [
        [
            [
                0.5755555968543882,
                -0.11582832736299586,
                0.0
            ],
            [
                -0.0,
                -0.0,
                0.4676545145644342,
                0.8839113388838857
            ]
        ]
    ],
    "difficulty": 0.0
}