{
    "target_eff_poses": [
        [
            [
                0.2719334065914154,
                -1.4824707508087158,
                0.144682839512825
            ],
            [
                0.6418264508247375,
                0.31795957684516907,
                -0.5842719078063965,
                0.3815584182739258
            ]
        ]
    ],
    "start_goal_config": [
        null
    ],
    "start_config": [
        [
            -2.9488119926943743,
            -2.8950968488736297,
            1.5217031164531278,
            -1.2133909263387883,
            -1.541121907699382,
            -2.726685814601443e-06
        ]
    ],
    "goal_config": [
        [
            -2.9261424339951922,
            -0.8556998534471157,
            1.2039372278775446,
            -1.8929497791534529,
            -1.4522399706120823,
            -5.688801195216414e-06
        ]
    ],
    "base_poses": [
        [
            [
                0.5395193964571625,
                -0.7828483181758022,
                0.0
            ],
            [
                -0.0,
                -0.0,
                0.3999934552562138,
                0.9165179953237117
            ]
        ]
    ],
    "difficulty": 0.0,
    "dynamic_speed": null
}