{
    "target_eff_poses": [
        [
            [
                0.5055176615715027,
                -0.5701555609703064,
                0.7561889886856079
            ],
            [
                0.04399096965789795,
                0.28546634316444397,
                -0.7239384651184082,
                0.6264877319335938
            ]
        ]
    ],
    "start_goal_config": [
        null
    ],
    "start_config": [
        [
            -3.73700667522818,
            -2.275242828009352,
            1.3023088089005461,
            -1.5102910558664857,
            -2.613105083944729,
            -3.7474391790217904e-05
        ]
    ],
    "goal_config": [
        [
            -3.4772844486219143,
            -2.353308892557368,
            1.2965086077697037,
            -1.498750797978215,
            -2.275367093109231,
            2.9922664527768393e-05
        ]
    ],
    "base_poses": [
        [
            [
                0.4694654564392715,
                -0.5596446997939225,
                0.0
            ],
            [
                0.0,
                0.0,
                0.9436511349395063,
                0.33094189146643527
            ]
        ]
    ],
    "difficulty": 0.0,
    "dynamic_speed": null
}