{
    "target_eff_poses": [
        [
            [
                0.6536549925804138,
                0.3678361773490906,
                0.14763155579566956
            ],
            [
                -0.6336454749107361,
                0.48354649543762207,
                0.025455987080931664,
                0.6033474802970886
            ]
        ],
        [
            [
                0.8619399666786194,
                -0.3140409588813782,
                0.16977249085903168
            ],
            [
                -0.3310207426548004,
                0.890510618686676,
                -0.008577202446758747,
                0.31199780106544495
            ]
        ]
    ],
    "start_goal_config": [
        null,
        null
    ],
    "start_config": [
        [
            -3.921600909635004,
            -1.7832009812727256,
            1.3182394924196097,
            -1.6324353641105174,
            -1.8148167785227118,
            1.967737515395638e-05
        ],
        [
            -4.573174944426522,
            -1.4941169508811605,
            2.137647002250056,
            -1.3806232919357513,
            -2.124524004825989,
            2.3513606868176375e-05
        ]
    ],
    "goal_config": [
        [
            -5.177228004352594,
            -0.9149221178277719,
            1.3707754295495485,
            -1.7525615953663214,
            -2.447577202935747,
            2.8602315141210977e-05
        ],
        [
            -3.7175553648453112,
            -1.9294294609223535,
            2.376665410305749,
            -1.082074167703349,
            -1.954172712000635,
            3.850786033405759e-13
        ]
    ],
    "base_poses": [
        [
            [
                0.27185884100586977,
                -0.19493160935247889,
                0.0
            ],
            [
                0.0,
                0.0,
                -0.072346799075081,
                0.997379536918414
            ]
        ],
        [
            [
                0.7266453225777894,
                -0.4240823191292933,
                0.0
            ],
            [
                0.0,
                0.0,
                0.8994944461375783,
                -0.4369321931005441
            ]
        ]
    ],
    "difficulty": 0.5683953400977076,
    "dynamic_speed": null,
    "ur5_count": 2,
    "id": "003702",
    "task_path": "/home/hqh2101/workspace-sharing-multiarm/src/data/8f14d7-hard-vlo-tasks/003702.json"
}