{
    "target_eff_poses": [
        [
            [
                -0.3366868495941162,
                -0.1306404173374176,
                0.6695749759674072
            ],
            [
                -0.2765578329563141,
                -0.05439239740371704,
                0.9563134908676147,
                0.07760033756494522
            ]
        ],
        [
            [
                0.36982032656669617,
                -0.44626089930534363,
                0.4381161034107208
            ],
            [
                0.6764445304870605,
                0.3107144236564636,
                -0.5976002216339111,
                -0.297914981842041
            ]
        ]
    ],
    "start_goal_config": [
        null,
        null
    ],
    "start_config": [
        [
            -1.9973838297813744,
            -1.6359766687590545,
            1.951373474191974,
            -1.4039253686511863,
            -1.200258678345624,
            -1.5579188794560464e-05
        ],
        [
            -3.302800255994668,
            -1.6918030491011187,
            1.3277142293393267,
            -1.6513214331971708,
            -1.6092060596190887,
            8.156415819987122e-06
        ]
    ],
    "goal_config": [
        [
            -2.974524072136114,
            -2.652370123090618,
            1.4295028501457336,
            -1.3472638828693828,
            -1.8459870902037883,
            1.7051533106418077e-05
        ],
        [
            -4.943718727671474,
            -1.95098387621998,
            1.8345004380670031,
            -1.3458354802906358,
            -2.463845777847715,
            2.983432261205658e-05
        ]
    ],
    "base_poses": [
        [
            [
                -0.42947173570191755,
                -0.06689331265410059,
                0.0
            ],
            [
                0.0,
                0.0,
                -0.02690111992371578,
                0.9996380993873982
            ]
        ],
        [
            [
                0.6870556261567466,
                -0.4484838732205848,
                0.0
            ],
            [
                -0.0,
                -0.0,
                0.7740011611472647,
                0.633184177426036
            ]
        ]
    ],
    "difficulty": 0.12911106934786695,
    "dynamic_speed": null
}