{
    "target_eff_poses": [
        [
            [
                -0.5772183537483215,
                0.6951664686203003,
                0.6020112037658691
            ],
            [
                -0.0002500193368177861,
                0.06091645359992981,
                0.5388030409812927,
                0.840226411819458
            ]
        ],
        [
            [
                -0.6371148228645325,
                0.1502443253993988,
                0.6163649559020996
            ],
            [
                0.024854404851794243,
                -0.1166229322552681,
                0.10862015932798386,
                0.9869057536125183
            ]
        ]
    ],
    "start_goal_config": [
        null,
        null
    ],
    "start_config": [
        [
            -2.9098557868100947,
            -2.5391385159518953,
            1.4758359284103302,
            -1.358542209693058,
            -1.485926407928463,
            -4.1660792480218095e-08
        ],
        [
            -1.4632634135835063,
            -1.121029871048551,
            1.3976103403843543,
            -1.7349728408604332,
            -0.8956964091776694,
            -2.7995033192050293e-05
        ]
    ],
    "goal_config": [
        [
            -3.2537678919066106,
            -3.0337600287907267,
            1.2916373909150176,
            -1.2775648967886608,
            -1.004746262138528,
            7.607837169194346e-06
        ],
        [
            -2.9095386427290735,
            -3.0328541465169407,
            1.0441802872400607,
            -1.3919732421005429,
            -1.671176366389629,
            -5.9172128538549195e-06
        ]
    ],
    "base_poses": [
        [
            [
                -0.17025978675797282,
                0.7454693083774355,
                0.0
            ],
            [
                0.0,
                0.0,
                0.9416594856970012,
                -0.3365671002888714
            ]
        ],
        [
            [
                -0.15272467208816354,
                0.2093119867104778,
                0.0
            ],
            [
                0.0,
                0.0,
                0.9990416562927594,
                -0.04376949841864641
            ]
        ]
    ],
    "difficulty": 0.5471644879149816,
    "dynamic_speed": null
}