{
    "target_eff_poses": [
        [
            [
                -0.011347964406013489,
                0.9531811475753784,
                0.48842883110046387
            ],
            [
                -0.6363480687141418,
                0.02563834749162197,
                0.696144163608551,
                0.3313414752483368
            ]
        ]
    ],
    "start_goal_config": [
        null
    ],
    "start_config": [
        [
            -3.521629815131926,
            -2.441344086427736,
            1.6309367967398605,
            -1.314465952738197,
            -1.9924063565017327,
            2.2775089192495394e-05
        ]
    ],
    "goal_config": [
        [
            -4.403642795455687,
            -1.7083187537698727,
            1.5086542535466645,
            -1.5610648124153264,
            -1.9747712393415726,
            3.459688459278145e-05
        ]
    ],
    "base_poses": [
        [
            [
                0.4065664520084562,
                0.7988280982371074,
                0.0
            ],
            [
                -0.0,
                -0.0,
                0.37906776802215814,
                0.9253689141346273
            ]
        ]
    ],
    "difficulty": 0.0,
    "dynamic_speed": null
}