{
    "target_eff_poses": [
        [
            [
                0.10119382292032242,
                -1.0645655393600464,
                0.4296153783798218
            ],
            [
                0.6849679350852966,
                0.2026529461145401,
                -0.3719911277294159,
                0.5927674770355225
            ]
        ]
    ],
    "start_goal_config": [
        null
    ],
    "start_config": [
        [
            -3.7064577047966027,
            -2.8139491700429624,
            2.2053351714776834,
            -0.852195886396906,
            -2.4653578777229272,
            1.4190940793564605e-05
        ]
    ],
    "goal_config": [
        [
            -1.5067235311288332,
            -1.66862829162594,
            1.6255004197787273,
            -1.507151039178144,
            -0.8480834873638489,
            -2.5339523720861315e-05
        ]
    ],
    "base_poses": [
        [
            [
                0.03263156362631359,
                -0.5853701259546024,
                0.0
            ],
            [
                0.0,
                0.0,
                -0.1676398164479083,
                0.9858483108172938
            ]
        ]
    ],
    "difficulty": 0.0,
    "dynamic_speed": null
}