{
    "target_eff_poses": [
        [
            [
                -0.08935253322124481,
                0.33439674973487854,
                0.22496049106121063
            ],
            [
                -0.513974666595459,
                0.7359386086463928,
                0.0043831695802509785,
                0.4406872093677521
            ]
        ],
        [
            [
                -0.2502397298812866,
                -0.06357424706220627,
                0.5409992933273315
            ],
            [
                -0.46941083669662476,
                0.38821732997894287,
                0.1292038857936859,
                0.7824622392654419
            ]
        ],
        [
            [
                0.4231894910335541,
                0.35004645586013794,
                0.48002368211746216
            ],
            [
                -0.3605242371559143,
                0.4835742712020874,
                0.08294575661420822,
                0.793283224105835
            ]
        ]
    ],
    "start_goal_config": [
        null,
        null,
        null
    ],
    "start_config": [
        [
            -1.6920107651178515,
            -2.081568753740159,
            1.8820833125312317,
            -1.2967094929169274,
            -0.7610918025247074,
            -1.0252888146102421e-05
        ],
        [
            -1.9400307098751488,
            -1.5544525432736302,
            1.6161677002851893,
            -1.5554207431670333,
            -1.1801866353858868,
            -2.042217915036127e-05
        ],
        [
            -2.759770358402048,
            -2.494250012928373,
            1.827314044634494,
            -1.19391390959664,
            -1.506877054813203,
            -3.896135331282594e-06
        ]
    ],
    "goal_config": [
        [
            -4.548559265479785,
            -1.8147428559869074,
            2.162902522711169,
            -1.2609363723863876,
            -2.1704972688447715,
            3.317467735948378e-17
        ],
        [
            -4.321682070588441,
            -2.2558284173672964,
            1.7412215213496112,
            -1.3169918320089926,
            -2.286945031111461,
            3.971516203042658e-05
        ],
        [
            -3.527570736410337,
            -2.614429026325939,
            1.8939347671852955,
            -1.126143402964448,
            -2.1072557620938803,
            7.31130659894416e-08
        ]
    ],
    "base_poses": [
        [
            [
                -0.29271989784179964,
                0.14538812299291115,
                0.0
            ],
            [
                0.0,
                0.0,
                -0.5290805142713535,
                0.8485716289261385
            ]
        ],
        [
            [
                -0.32492121057430856,
                -0.23912807434258332,
                0.0
            ],
            [
                0.0,
                0.0,
                -0.44306774985749087,
                0.8964881310068862
            ]
        ],
        [
            [
                0.4161341760381807,
                0.2854526429479607,
                0.0
            ],
            [
                0.0,
                0.0,
                -0.8443742097416251,
                0.5357538557240685
            ]
        ]
    ],
    "difficulty": 0.815103921753033,
    "dynamic_speed": null,
    "ur5_count": 3,
    "id": "005383",
    "task_path": "/home/huy/programming/projects/workspace-sharing-multiarm/src/data/8f14d7-hard-vlo-tasks/005383.json"
}