{
    "target_eff_poses": [
        [
            [
                -0.09049379080533981,
                -0.6900281310081482,
                0.2419838011264801
            ],
            [
                0.6441698670387268,
                0.5525615811347961,
                -0.4881805181503296,
                0.2034716159105301
            ]
        ]
    ],
    "start_goal_config": [
        null
    ],
    "start_config": [
        [
            -3.05243298046123,
            -3.104950906449868,
            0.925509745931521,
            -1.4093888807044403,
            -1.3882652162251798,
            8.947727772601729e-06
        ]
    ],
    "goal_config": [
        [
            -4.133610422584607,
            -1.596991074411125,
            1.906124613868047,
            -1.4237013531407106,
            -1.8848828487065548,
            2.3362195108728227e-05
        ]
    ],
    "base_poses": [
        [
            [
                0.02480006059080697,
                -0.3080159987490834,
                0.0
            ],
            [
                0.0,
                0.0,
                0.866411843906792,
                0.4993300679290529
            ]
        ]
    ],
    "difficulty": 0.0
}