{
    "target_eff_poses": [
        [
            [
                0.2847296893596649,
                0.7232779264450073,
                0.7859992384910583
            ],
            [
                -0.21069692075252533,
                0.054577093571424484,
                0.7738457918167114,
                0.5948031544685364
            ]
        ],
        [
            [
                -0.2728091776371002,
                -0.5796260833740234,
                0.3738662898540497
            ],
            [
                -0.5421943068504333,
                -0.538611114025116,
                0.602834939956665,
                -0.22915811836719513
            ]
        ]
    ],
    "start_goal_config": [
        null,
        null
    ],
    "start_config": [
        [
            -3.3194653997603334,
            -2.3329429984675447,
            1.1737957684052904,
            -1.5601537012738156,
            -2.6500909854401185,
            -4.89592558461256e-05
        ],
        [
            -3.27928907288087,
            -2.201440372954933,
            1.1503196509810256,
            -1.6127772986229825,
            -1.755443080475592,
            1.4993969913099785e-05
        ]
    ],
    "goal_config": [
        [
            -3.2430901141181367,
            -2.344808308747344,
            1.1945808733978487,
            -1.5525381221020367,
            -1.972715202175084,
            3.082380645791789e-05
        ],
        [
            -4.302568226652183,
            -1.8897994954000565,
            1.8537466148135902,
            -1.3657780468604488,
            -1.9896117189743971,
            2.1508990218481496e-05
        ]
    ],
    "base_poses": [
        [
            [
                0.33783224751220264,
                0.7499764647393732,
                0.0
            ],
            [
                0.0,
                0.0,
                -0.3927393044758507,
                0.919649845712935
            ]
        ],
        [
            [
                -0.1870383929754793,
                -0.25395816694575213,
                0.0
            ],
            [
                0.0,
                0.0,
                0.9140547399447623,
                0.4055908435659181
            ]
        ]
    ],
    "difficulty": 0.15085112385968213,
    "dynamic_speed": null
}