{
    "target_eff_poses": [
        [
            [
                -0.2873501479625702,
                0.6709213256835938,
                0.5657858848571777
            ],
            [
                -0.49111810326576233,
                -0.3862091898918152,
                0.7359368801116943,
                0.2608494162559509
            ]
        ],
        [
            [
                -0.09109053760766983,
                0.21254423260688782,
                0.22528719902038574
            ],
            [
                0.44219115376472473,
                0.7321391105651855,
                -0.1458587795495987,
                0.4971564710140228
            ]
        ],
        [
            [
                -0.16793939471244812,
                -1.3858901262283325,
                0.413480281829834
            ],
            [
                0.6124234795570374,
                0.0876656323671341,
                -0.5560617446899414,
                0.5550205111503601
            ]
        ]
    ],
    "start_goal_config": [
        null,
        null,
        null
    ],
    "start_config": [
        [
            -2.335738225158889,
            -1.4896143093273189,
            1.6779588713408866,
            -1.5466382591784367,
            -1.3397020233678822,
            -9.793329196667067e-06
        ],
        [
            -3.1169816270249133,
            -2.3651482543095077,
            1.140116089011327,
            -1.5747800792343505,
            -1.884010560734873,
            1.9583927993760776e-05
        ],
        [
            -4.291173550128652,
            -1.2995700723656705,
            1.220338086785152,
            -1.7839382167163955,
            -1.8655133514383186,
            2.0227538915492325e-05
        ]
    ],
    "goal_config": [
        [
            -4.626751399629089,
            -2.1544721778144353,
            1.7089984044548647,
            -1.3463809292910154,
            -2.577815327866392,
            3.4077268405219626e-05
        ],
        [
            -2.244102542266474,
            -1.561180830166317,
            1.9087662449813627,
            -1.436867823009301,
            -1.3128400284030703,
            -5.583592422125593e-07
        ],
        [
            -1.5155403458737715,
            -1.207181771912947,
            1.1916122264396871,
            -1.7919175157912206,
            -0.9285093222700928,
            -2.928622517996868e-05
        ]
    ],
    "base_poses": [
        [
            [
                -0.07174044623873554,
                0.7429843209921536,
                0.0
            ],
            [
                -0.0,
                -0.0,
                0.7867132457016113,
                0.6173186122559696
            ]
        ],
        [
            [
                -0.4653366967788424,
                0.4101236536501742,
                0.0
            ],
            [
                -0.0,
                -0.0,
                0.6500837914876428,
                0.7598625297019527
            ]
        ],
        [
            [
                0.07874113113649073,
                -0.7460224668614673,
                0.0
            ],
            [
                0.0,
                0.0,
                -0.3426325820853251,
                0.9394694852381013
            ]
        ]
    ],
    "difficulty": 0.6295112781954887,
    "dynamic_speed": null,
    "ur5_count": 3,
    "id": "006841",
    "task_path": "/home/hqh2101/workspace-sharing-multiarm/src/data/8f14d7-hard-vlo-tasks/006841.json"
}