{
    "target_eff_poses": [
        [
            [
                0.22235587239265442,
                -0.6071472764015198,
                0.31194257736206055
            ],
            [
                0.7553032636642456,
                0.2671118676662445,
                -0.5979791283607483,
                -0.024273497983813286
            ]
        ]
    ],
    "start_goal_config": [
        null
    ],
    "start_config": [
        [
            -3.8698738856206316,
            -1.6743868726688382,
            1.4810821408195671,
            -1.5847791458869644,
            -1.7785682478201117,
            2.2092088493835582e-05
        ]
    ],
    "goal_config": [
        [
            -3.2084915832733216,
            -2.6742440353461094,
            2.2149062744696923,
            -0.8238437395016217,
            -1.9512863875581734,
            5.837906642649371e-06
        ]
    ],
    "base_poses": [
        [
            [
                0.23181788904913625,
                -0.5405226582309604,
                0.0
            ],
            [
                -0.0,
                -0.0,
                0.18210599653797963,
                0.9832789055120167
            ]
        ]
    ],
    "difficulty": 0.0,
    "dynamic_speed": null
}