{
    "target_eff_poses": [
        [
            [
                0.3488527834415436,
                0.45622527599334717,
                0.21281921863555908
            ],
            [
                0.9130772948265076,
                -0.0020643868483603,
                -0.3014332950115204,
                -0.2746337056159973
            ]
        ]
    ],
    "start_goal_config": [
        null
    ],
    "start_config": [
        [
            -2.667249072587262,
            -1.2233521406801926,
            1.8696733787720188,
            -1.5413914122363748,
            -1.4346666981098068,
            -5.566178143186345e-06
        ]
    ],
    "goal_config": [
        [
            -4.708602928302882,
            -1.8129377189372795,
            2.2165688935549412,
            -1.2436606579952605,
            -2.3074296796331737,
            2.3904053970449756e-05
        ]
    ],
    "base_poses": [
        [
            [
                0.5590947704737861,
                0.2933862804017453,
                0.0
            ],
            [
                -0.0,
                -0.0,
                0.4012961011026352,
                0.9159483824101791
            ]
        ]
    ],
    "difficulty": 0.0,
    "dynamic_speed": null,
    "ur5_count": 1,
    "id": "007500",
    "task_path": "/home/hqh2101/workspace-sharing-multiarm/src/data/8f14d7-hard-vlo-tasks/007500.json"
}