{
    "target_eff_poses": [
        [
            [
                0.5853159427642822,
                0.4984603226184845,
                0.7977892756462097
            ],
            [
                -0.018697086721658707,
                0.17102406919002533,
                -0.18908986449241638,
                0.9667710065841675
            ]
        ],
        [
            [
                1.3699135780334473,
                -0.08539202064275742,
                0.20939387381076813
            ],
            [
                0.05712607875466347,
                0.7379230260848999,
                0.2795791029930115,
                0.6115894913673401
            ]
        ]
    ],
    "start_goal_config": [
        null,
        null
    ],
    "start_config": [
        [
            -2.8364318960747057,
            -2.9850553374077986,
            1.9692409404539957,
            -0.8786057344815563,
            -1.7165755730215748,
            7.87087223446908e-06
        ],
        [
            -2.7046209609618157,
            -3.1114659376986835,
            1.5777180506479886,
            -1.0921112875552725,
            -2.066854081755392,
            3.088386671910605e-05
        ]
    ],
    "goal_config": [
        [
            -3.0948885489700855,
            -2.3854696749277715,
            1.15266106029531,
            -1.5629693864907532,
            -1.8728989199929669,
            2.2961414813021e-05
        ],
        [
            -1.7319218548987407,
            -1.0276690162066064,
            1.3422541242217718,
            -1.789635264493574,
            -1.064766219632297,
            -2.373120550259738e-05
        ]
    ],
    "base_poses": [
        [
            [
                0.6095567524222945,
                0.4256926913003598,
                0.0
            ],
            [
                0.0,
                0.0,
                0.9978589458101905,
                0.065402784853363
            ]
        ],
        [
            [
                0.794525271074469,
                -0.4797710673394557,
                0.0
            ],
            [
                -0.0,
                -0.0,
                0.8632666833126049,
                0.5047480891320483
            ]
        ]
    ],
    "difficulty": 0.26793943383805136,
    "dynamic_speed": null,
    "ur5_count": 2,
    "id": "008344",
    "task_path": "/home/huy/programming/projects/workspace-sharing-multiarm/src/data/8f14d7-hard-vlo-tasks/008344.json"
}