{
    "target_eff_poses": [
        [
            [
                0.8127210140228271,
                0.09730590879917145,
                0.19922496378421783
            ],
            [
                0.6093620657920837,
                0.7527042031288147,
                0.1797245442867279,
                0.17266526818275452
            ]
        ],
        [
            [
                -0.5438233613967896,
                0.2039170116186142,
                0.8125181794166565
            ],
            [
                0.05635448545217514,
                0.16836929321289062,
                -0.712685763835907,
                0.6786419749259949
            ]
        ]
    ],
    "start_goal_config": [
        null,
        null
    ],
    "start_config": [
        [
            -2.8698727610669517,
            -2.5258355873025287,
            1.1213255927524122,
            -1.5391718763096882,
            -1.9219311063929903,
            2.172323576666242e-05
        ],
        [
            -4.883953375171897,
            -2.1573084240991496,
            2.1647038021126592,
            -1.1260052141220536,
            -2.887265302347571,
            1.776564411785664e-05
        ]
    ],
    "goal_config": [
        [
            -1.6817137319464746,
            -2.520765537857424,
            2.645887865922993,
            -0.628879635067243,
            -0.08482403251729878,
            -6.927884754886719e-06
        ],
        [
            -3.224657757958012,
            -2.324105459674419,
            1.1294984124019163,
            -1.5899743864660003,
            -2.057756652578738,
            3.651504410509772e-05
        ]
    ],
    "base_poses": [
        [
            [
                0.7635367139183853,
                -0.14942437528976082,
                0.0
            ],
            [
                -0.0,
                -0.0,
                0.7853724721479822,
                0.6190234890471984
            ]
        ],
        [
            [
                -0.5850775642722708,
                0.17808183600025185,
                0.0
            ],
            [
                -0.0,
                -0.0,
                0.8654010218283792,
                0.5010799052231064
            ]
        ]
    ],
    "difficulty": 0.04849168311248943,
    "dynamic_speed": null
}