{
    "target_eff_poses": [
        [
            [
                -0.16889676451683044,
                0.5906303524971008,
                0.37028756737709045
            ],
            [
                -0.5266162753105164,
                0.20687797665596008,
                0.6097795367240906,
                0.5550186634063721
            ]
        ],
        [
            [
                1.176285982131958,
                -0.36739805340766907,
                0.4622706472873688
            ],
            [
                0.28088143467903137,
                0.6037505269050598,
                -0.13091596961021423,
                0.7344739437103271
            ]
        ]
    ],
    "start_goal_config": [
        null,
        null
    ],
    "start_config": [
        [
            -2.270378277614549,
            -1.9881037936442179,
            1.4120209404844684,
            -1.5359130823160019,
            -1.225565698906249,
            -1.494737271919778e-05
        ],
        [
            -2.946232009339433,
            -1.386869310658151,
            1.3457946719721574,
            -1.7139611875436966,
            -1.4924866933209082,
            -5.502391881775285e-07
        ]
    ],
    "goal_config": [
        [
            -2.855635741886459,
            -3.146886794618241,
            1.9669135103841267,
            -0.7588247540385364,
            -1.9348955301445194,
            5.251643240115997e-06
        ],
        [
            -2.2754767900502353,
            -1.7960830924728184,
            1.6089020550632047,
            -1.4970357469800368,
            -1.3117428436070435,
            -1.1338576650707643e-05
        ]
    ],
    "base_poses": [
        [
            [
                -0.1760002995884733,
                0.7471791372385739,
                0.0
            ],
            [
                0.0,
                0.0,
                -0.6437178824518559,
                0.7652628880402463
            ]
        ],
        [
            [
                0.7680741573065049,
                -0.25498800882128003,
                0.0
            ],
            [
                -0.0,
                -0.0,
                0.7391547545979784,
                0.6735356328771347
            ]
        ]
    ],
    "difficulty": 0.05291353383458647,
    "dynamic_speed": null
}